rejgoo/__init__.py
rejgoo/newt_raph.py
rejgoo/parser.py
rejgoo/rejgoo.py
rejgoo/riazi.py
rejgoo/solver.py
rejgoo-0.0.6.dist-info/licenses/LICENSE
rejgoo-0.0.6.dist-info/METADATA
rejgoo-0.0.6.dist-info/WHEEL
rejgoo-0.0.6.dist-info/top_level.txt
rejgoo-0.0.6.dist-info/RECORD
