Metadata-Version: 2.4
Name: rejgoo
Version: 0.0.6
Summary: Python package that solves mathematical equations
Author-email: Mahdi Hajebi <merto071@yahoo.com>
Maintainer-email: Mahdi Hajebi <merto071@yahoo.com>
License: MIT license
Project-URL: bugs, https://github.com/mertomax/rejgoo/issues
Project-URL: changelog, https://github.com/mertomax/rejgoo/blob/master/changelog.md
Project-URL: homepage, https://github.com/mertomax/rejgoo
Requires-Python: >=3.10
License-File: LICENSE
Requires-Dist: numpy<3.0.0,>=2.0.0
Requires-Dist: CoolProp<7.0.0,>=6.7.0
Provides-Extra: dev
Requires-Dist: coverage; extra == "dev"
Requires-Dist: pytest; extra == "dev"
Dynamic: license-file
